__init__.py
gpx_vis.py
gpx_vis-0.3.6.dist-info/LICENSE
gpx_vis-0.3.6.dist-info/METADATA
gpx_vis-0.3.6.dist-info/WHEEL
gpx_vis-0.3.6.dist-info/top_level.txt
gpx_vis-0.3.6.dist-info/RECORD
