Metadata-Version: 2.1
Name: gpx_vis
Version: 0.3.6
Summary: Visualising your Komoot/Strava tours
Author-email: Jia Wei Teh <jiaweiteh.astro@gmail.com>
Classifier: Programming Language :: Python :: 3
Classifier: Operating System :: OS Independent
Requires-Python: >=3.8
License-File: LICENSE
Requires-Dist: folium
Requires-Dist: numpy
Requires-Dist: pandas
Requires-Dist: humanfriendly
Requires-Dist: reverse-geocode
Requires-Dist: matplotlib
Requires-Dist: vincenty
Requires-Dist: altair
Requires-Dist: gpxpy
